django_sql_debug/__init__.py
django_sql_debug/apps.py
django_sql_debug/middlewares.py
django_sql_debug/output.py
django_sql_debug/sql.py
django_sql_debug/test.py
django_sql_debug-0.0.3.dist-info/LICENSE
django_sql_debug-0.0.3.dist-info/METADATA
django_sql_debug-0.0.3.dist-info/WHEEL
django_sql_debug-0.0.3.dist-info/top_level.txt
django_sql_debug-0.0.3.dist-info/RECORD
