Metadata-Version: 2.1
Name: django-sql-debug
Version: 0.0.3
Summary: Output in the console the executed SQL of queries made by Django's ORM
Home-page: https://github.com/mscansian/django-sql-debug
Author: Matheus Cansian
Author-email: dev@drpexe.com
Classifier: Programming Language :: Python :: 3
Classifier: License :: OSI Approved :: MIT License
Classifier: Operating System :: OS Independent
Requires-Python: >=3.6
License-File: LICENSE
Requires-Dist: Django (>=3.2.4)
